manicrypt/__init__.py
manicrypt/mcrypt.py
manicrypt-0.0.3.dist-info/LICENSE
manicrypt-0.0.3.dist-info/METADATA
manicrypt-0.0.3.dist-info/WHEEL
manicrypt-0.0.3.dist-info/top_level.txt
manicrypt-0.0.3.dist-info/RECORD
