Metadata-Version: 2.1
Name: manicrypt
Version: 0.0.3
Summary: a simple cryptography module built to test the pip upload
Home-page: https://github.com/MANIKANDANMLT/manicrypt.git
Author: ManikandanSrinivasalu
Author-email: s.manikandan11306@gmail.com
Classifier: Programming Language :: Python :: 3
Classifier: License :: OSI Approved :: MIT License
Classifier: Operating System :: OS Independent
Requires-Python: >=3.6
License-File: LICENSE
